tuStockSpider/__init__.py
tuStockSpider/stock_run.py
tuStockSpider/stock_vas.py
tuStockSpider-0.15.dist-info/DESCRIPTION.rst
tuStockSpider-0.15.dist-info/METADATA
tuStockSpider-0.15.dist-info/RECORD
tuStockSpider-0.15.dist-info/WHEEL
tuStockSpider-0.15.dist-info/metadata.json
tuStockSpider-0.15.dist-info/top_level.txt
tuStockSpider-0.15.dist-info/zip-safe
